gemini/__init__.py
gemini/commit_code.py
gemini/review_code-precious.py
gemini/review_code-precious1.py
gemini/review_code.py
gemini/review_code2.py
gemini_code_review-1.0.2.dist-info/METADATA
gemini_code_review-1.0.2.dist-info/WHEEL
gemini_code_review-1.0.2.dist-info/entry_points.txt
gemini_code_review-1.0.2.dist-info/top_level.txt
gemini_code_review-1.0.2.dist-info/RECORD
