Metadata-Version: 2.1
Name: gemini-code-review
Version: 1.0.2
Summary: code review via diff
Home-page: https://xxx.com
Author: xuwuqiang
Author-email: xwqiang2008@outlook.com
License: MIT Licence
Keywords: gitlab,ai,code review
Platform: any
Requires-Dist: google-ai-generativelanguage==0.6.10
Requires-Dist: google-generativeai
Requires-Dist: github3.py==1.3.0
Requires-Dist: unidiff
Requires-Dist: setuptools==65.6.3
